lovpy/__init__.py
lovpy/__main__.py
lovpy/config.py
lovpy/exception_handler.py
lovpy/exceptions.py
lovpy/lovpy_utils.py
lovpy/runner.py
lovpy/evaluation/__init__.py
lovpy/evaluation/evaluate_on_examples.py
lovpy/evaluation/evaluate_on_synthetics.py
lovpy/evaluation/evaluation.py
lovpy/graphs/__init__.py
lovpy/graphs/colorizable_multidigraph.py
lovpy/graphs/dynamic_temporal_graph.py
lovpy/graphs/logical_operators.py
lovpy/graphs/timed_property_graph.py
lovpy/graphs/timestamps.py
lovpy/importer/__init__.py
lovpy/importer/file_converter.py
lovpy/importer/gherkin_importer.py
lovpy/importer/lovpy_ignore.py
lovpy/importer/text_converter.py
lovpy/logic/__init__.py
lovpy/logic/next_theorem_selectors.py
lovpy/logic/properties.py
lovpy/logic/prover.py
lovpy/models/__init__.py
lovpy/models/callbacks.py
lovpy/models/dataset_generator.py
lovpy/models/gnn_model.py
lovpy/models/graph_neural_theorem_selector.py
lovpy/models/io.py
lovpy/models/neural_theorem_selector.py
lovpy/models/simple_model.py
lovpy/models/theorem_proving_model.py
lovpy/models/train_config.py
lovpy/models/train_model.py
lovpy/monitor/__init__.py
lovpy/monitor/monitored_predicate.py
lovpy/monitor/program.py
lovpy/monitor/time_source.py
lovpy/monitor/wrappers.py
lovpy/tools/__init__.py
lovpy/tools/path.py
lovpy/visualization_strategies/__init__.py
lovpy/visualization_strategies/set_full_visualization_scheme.py
lovpy/visualization_strategies/set_proving_process_visualization_enabled.py
tests/__init__.py
tests/visualize_samples.py
tests/lovpy/__init__.py
tests/lovpy/graphs/__init__.py
tests/lovpy/graphs/test_colorizable_digraph.py
tests/lovpy/graphs/test_dynamic_temporal_graph.py
tests/lovpy/graphs/test_timed_property_graph.py
tests/lovpy/graphs/test_timestamps.py
tests/lovpy/importer/__init__.py
tests/lovpy/importer/sample_properties.py
tests/lovpy/importer/test_file_converter.py
tests/lovpy/importer/test_gherkin_importer.py
tests/lovpy/logic/__init__.py
tests/lovpy/logic/test_properties.py
lovpy-0.1.0.dist-info/LICENSE
lovpy-0.1.0.dist-info/METADATA
lovpy-0.1.0.dist-info/NOTICE
lovpy-0.1.0.dist-info/WHEEL
lovpy-0.1.0.dist-info/top_level.txt
lovpy-0.1.0.dist-info/RECORD
