Metadata-Version: 2.1
Name: lovpy
Version: 0.1.0
Summary: A simple-to-use logic verification library.
Home-page: https://github.com/dkarageo/lovpy
Author: Dimitrios S. Karageorgiou
Author-email: karageods@gmail.com
Project-URL: Bug Tracker, https://github.com/dkarageo/lovpy/issues
Classifier: Programming Language :: Python :: 3
Classifier: License :: OSI Approved :: Mozilla Public License 2.0 (MPL 2.0)
Classifier: Operating System :: OS Independent
Classifier: Development Status :: 3 - Alpha
Requires-Python: >=3.5
License-File: LICENSE
License-File: NOTICE
Requires-Dist: networkx
Requires-Dist: matplotlib
Requires-Dist: numpy
Requires-Dist: pandas
Requires-Dist: sklearn
